halring/__init__.py
halring/_unittest/666666.py
halring/_unittest/77777.py
halring/_unittest/__init__.py
halring/_unittest/cty.py
halring/_unittest/dk.py
halring/_unittest/test_apollo_opr_util.py
halring/_unittest/test_artifactory_lib_util.py
halring/_unittest/test_case_config_parser_util.py
halring/_unittest/test_confluence_util.py
halring/_unittest/test_const_variable.py
halring/_unittest/test_datetime_util.py
halring/_unittest/test_docx_util.py
halring/_unittest/test_excel_util.py
halring/_unittest/test_ftp.py
halring/_unittest/test_git.py
halring/_unittest/test_jenkins_util.py
halring/_unittest/test_jira.py
halring/_unittest/test_json_util.py
halring/_unittest/test_linux.py
halring/_unittest/test_linux_util.py
halring/_unittest/test_logging_util.py
halring/_unittest/test_loguru_util.py
halring/_unittest/test_mssql_util.py
halring/_unittest/test_mysql_util.py
halring/_unittest/test_os_util.py
halring/_unittest/test_plink_util.py
halring/_unittest/test_rabbitmq_util_consumer.py
halring/_unittest/test_rabbitmq_util_publisher.py
halring/_unittest/test_rds_api_util.py
halring/_unittest/test_redis.py
halring/_unittest/test_reg_util.py
halring/_unittest/test_ssh2_util.py
halring/_unittest/test_string_util.py
halring/_unittest/test_svn.py
halring/_unittest/test_windows_exec.py
halring/_unittest/test_windows_os_util.py
halring/_unittest/test_xml_util.py
halring/_unittest/tt.py
halring/apollo/__init__.py
halring/apollo/halring_apollo_opr.py
halring/artifactory_lib/__init__.py
halring/artifactory_lib/halring_artifactory_lib.py
halring/caseconfig/__init__.py
halring/caseconfig/halring_parser.py
halring/common/__init__.py
halring/common/halring_common.py
halring/common/halring_const_variable.py
halring/common/halring_datetime.py
halring/common/halring_env_config_parser.py
halring/common/halring_string.py
halring/confluence/__init__.py
halring/confluence/halring_confluence.py
halring/crypto/__init__.py
halring/crypto/halring_crypt.py
halring/date_time/__init__.py
halring-2.3.2.dist-info/LICENSE
halring-2.3.2.dist-info/METADATA
halring-2.3.2.dist-info/WHEEL
halring-2.3.2.dist-info/top_level.txt
halring-2.3.2.dist-info/RECORD
