Metadata-Version: 2.1
Name: halring
Version: 2.3.2
Summary: python常用底层库封装
Home-page: https://www.python.org
Author: peixiaodong
License: MIT Licence
Classifier: Programming Language :: Python :: 3
Classifier: License :: OSI Approved :: MIT License
Classifier: Operating System :: OS Independent
Requires-Python: >=3.6.0
License-File: LICENSE
Requires-Dist: twine (==3.8.0)
Requires-Dist: loguru (==0.6.0)
Requires-Dist: rsa (==4.9)
Requires-Dist: artifactory (==0.1.17)
Requires-Dist: jira (==3.2.0)
Requires-Dist: requests
Requires-Dist: atlassian-python-api (==3.32.2)
Requires-Dist: jieba (==0.42.1)
Requires-Dist: xlrd (==2.0.1)
Requires-Dist: openpyxl (==2.5.6)
Requires-Dist: python-jenkins (==1.7.0)
Requires-Dist: paramiko (==3.0.0)
Requires-Dist: PyMySQL (==1.0.2)
Requires-Dist: chardet (==5.0.0)
Requires-Dist: pymssql (==2.3.0)
Requires-Dist: pika (==1.3.1)
Requires-Dist: pandas (==1.1.5)
Requires-Dist: urllib3 (==1.26.0)
Requires-Dist: redis (==4.3.5)
Requires-Dist: python-docx (==0.8.10)
Requires-Dist: pypandoc (==1.11)
Requires-Dist: pdfkit (==1.0.0)
